alexandernikitin/__init__.py
alexandernikitin/client.py
alexandernikitin/core/__init__.py
alexandernikitin/core/api_error.py
alexandernikitin/core/client_wrapper.py
alexandernikitin/core/datetime_utils.py
alexandernikitin/core/file.py
alexandernikitin/core/force_multipart.py
alexandernikitin/core/http_client.py
alexandernikitin/core/http_response.py
alexandernikitin/core/jsonable_encoder.py
alexandernikitin/core/pydantic_utilities.py
alexandernikitin/core/query_encoder.py
alexandernikitin/core/remove_none_from_dict.py
alexandernikitin/core/request_options.py
alexandernikitin/core/serialization.py
alexandernikitin/environment.py
alexandernikitin/errors/__init__.py
alexandernikitin/errors/bad_request_error.py
alexandernikitin/errors/method_not_allowed_error.py
alexandernikitin/errors/not_found_error.py
alexandernikitin/plant/__init__.py
alexandernikitin/plant/client.py
alexandernikitin/plant/raw_client.py
alexandernikitin/plant/types/__init__.py
alexandernikitin/plant/types/search_plants_by_status_request_status.py
alexandernikitin/py.typed
alexandernikitin/types/__init__.py
alexandernikitin/types/plant.py
alexandernikitin/types/plant_response.py
alexandernikitin/types/plant_status.py
alexandernikitin/types/user.py
alexandernikitin/types/user_auth_response.py
alexandernikitin/user/__init__.py
alexandernikitin/user/client.py
alexandernikitin/user/raw_client.py
alexandernikitin/version.py
alexander_nikitin_thenvoi_plantstore_python_sdk-0.0.2.dist-info/METADATA
alexander_nikitin_thenvoi_plantstore_python_sdk-0.0.2.dist-info/WHEEL
alexander_nikitin_thenvoi_plantstore_python_sdk-0.0.2.dist-info/RECORD
